sky130ph/__init__.py
sky130ph/components.py
sky130ph/config.py
sky130ph-0.0.6.dist-info/LICENSE
sky130ph-0.0.6.dist-info/METADATA
sky130ph-0.0.6.dist-info/WHEEL
sky130ph-0.0.6.dist-info/top_level.txt
sky130ph-0.0.6.dist-info/RECORD
