Metadata-Version: 2.1
Name: sky130ph
Version: 0.0.6
Summary: Skywater photonics PDK for the 130nm fab foundry
Home-page: https://github.com/joamatab/cookiecutter-pypackage-minimal
Author: SkandanC
Author-email: s39chand@uwaterloo.ca
License: MIT
Classifier: Development Status :: 2 - Pre-Alpha
Classifier: License :: OSI Approved :: MIT License
Classifier: Programming Language :: Python
Classifier: Programming Language :: Python :: 3.7
Requires-Python: >=3.6
License-File: LICENSE
Requires-Dist: gdsfactory
